<?xml version="1.0" encoding="utf-8"?>
<!--항상 켜기-->
<Script>
    <ScriptOrder>0</ScriptOrder>
    <ScriptType>Color</ScriptType>
    <ScriptDataList>
        <ScriptData>
            <ScriptBright>OP_START</ScriptBright>
            <ScriptDuration>0</ScriptDuration>
        </ScriptData>
        <ScriptData>
            <ScriptBright>0</ScriptBright>
            <ScriptColor>12517376</ScriptColor>
            <ScriptDuration>200</ScriptDuration>
        </ScriptData>
        <ScriptData>
            <ScriptBright>0</ScriptBright>
            <ScriptColor>11864576</ScriptColor>
            <ScriptDuration>10</ScriptDuration>
        </ScriptData>
        <ScriptData>
            <ScriptBright>0</ScriptBright>
            <ScriptColor>11211776</ScriptColor>
            <ScriptDuration>10</ScriptDuration>
        </ScriptData>
        <ScriptData>
            <ScriptBright>0</ScriptBright>
            <ScriptColor>10558976</ScriptColor>
            <ScriptDuration>10</ScriptDuration>
        </ScriptData>
        <ScriptData>
            <ScriptBright>0</ScriptBright>
            <ScriptColor>9906176</ScriptColor>
            <ScriptDuration>10</ScriptDuration>
        </ScriptData>
        <ScriptData>
            <ScriptBright>0</ScriptBright>
            <ScriptColor>9253376</ScriptColor>
            <ScriptDuration>10</ScriptDuration>
        </ScriptData>
        <ScriptData>
            <ScriptBright>0</ScriptBright>
            <ScriptColor>8600576</ScriptColor>
            <ScriptDuration>10</ScriptDuration>
        </ScriptData>
        <ScriptData>
            <ScriptBright>0</ScriptBright>
            <ScriptColor>7947776</ScriptColor>
            <ScriptDuration>10</ScriptDuration>
        </ScriptData>
        <ScriptData>
            <ScriptBright>0</ScriptBright>
            <ScriptColor>7294976</ScriptColor>
            <ScriptDuration>10</ScriptDuration>
        </ScriptData>
        <ScriptData>
            <ScriptBright>0</ScriptBright>
            <ScriptColor>6642176</ScriptColor>
            <ScriptDuration>10</ScriptDuration>
        </ScriptData>
        <ScriptData>
            <ScriptBright>0</ScriptBright>
            <ScriptColor>5989376</ScriptColor>
            <ScriptDuration>10</ScriptDuration>
        </ScriptData>
        <ScriptData>
            <ScriptBright>0</ScriptBright>
            <ScriptColor>5336576</ScriptColor>
            <ScriptDuration>10</ScriptDuration>
        </ScriptData>
        <ScriptData>
            <ScriptBright>0</ScriptBright>
            <ScriptColor>4683776</ScriptColor>
            <ScriptDuration>10</ScriptDuration>
        </ScriptData>
        <ScriptData>
            <ScriptBright>0</ScriptBright>
            <ScriptColor>4030976</ScriptColor>
            <ScriptDuration>10</ScriptDuration>
        </ScriptData>
        <ScriptData>
            <ScriptBright>0</ScriptBright>
            <ScriptColor>3378176</ScriptColor>
            <ScriptDuration>10</ScriptDuration>
        </ScriptData>
        <ScriptData>
            <ScriptBright>0</ScriptBright>
            <ScriptColor>2725376</ScriptColor>
            <ScriptDuration>10</ScriptDuration>
        </ScriptData>
        <ScriptData>
            <ScriptBright>0</ScriptBright>
            <ScriptColor>2072576</ScriptColor>
            <ScriptDuration>10</ScriptDuration>
        </ScriptData>
        <ScriptData>
            <ScriptBright>0</ScriptBright>
            <ScriptColor>1419776</ScriptColor>
            <ScriptDuration>10</ScriptDuration>
        </ScriptData>
        <ScriptData>
            <ScriptBright>0</ScriptBright>
            <ScriptColor>766976</ScriptColor>
            <ScriptDuration>10</ScriptDuration>
        </ScriptData>
        <ScriptData>
            <ScriptBright>0</ScriptBright>
            <ScriptColor>48896</ScriptColor>
            <ScriptDuration>200</ScriptDuration>
        </ScriptData>
        <ScriptData>
            <ScriptBright>0</ScriptBright>
            <ScriptColor>46346</ScriptColor>
            <ScriptDuration>10</ScriptDuration>
        </ScriptData>
        <ScriptData>
            <ScriptBright>0</ScriptBright>
            <ScriptColor>43796</ScriptColor>
            <ScriptDuration>10</ScriptDuration>
        </ScriptData>
        <ScriptData>
            <ScriptBright>0</ScriptBright>
            <ScriptColor>41246</ScriptColor>
            <ScriptDuration>10</ScriptDuration>
        </ScriptData>
        <ScriptData>
            <ScriptBright>0</ScriptBright>
            <ScriptColor>38696</ScriptColor>
            <ScriptDuration>10</ScriptDuration>
        </ScriptData>
        <ScriptData>
            <ScriptBright>0</ScriptBright>
            <ScriptColor>36146</ScriptColor>
            <ScriptDuration>10</ScriptDuration>
        </ScriptData>
        <ScriptData>
            <ScriptBright>0</ScriptBright>
            <ScriptColor>33596</ScriptColor>
            <ScriptDuration>10</ScriptDuration>
        </ScriptData>
        <ScriptData>
            <ScriptBright>0</ScriptBright>
            <ScriptColor>31046</ScriptColor>
            <ScriptDuration>10</ScriptDuration>
        </ScriptData>
        <ScriptData>
            <ScriptBright>0</ScriptBright>
            <ScriptColor>28496</ScriptColor>
            <ScriptDuration>10</ScriptDuration>
        </ScriptData>
        <ScriptData>
            <ScriptBright>0</ScriptBright>
            <ScriptColor>25946</ScriptColor>
            <ScriptDuration>10</ScriptDuration>
        </ScriptData>
        <ScriptData>
            <ScriptBright>0</ScriptBright>
            <ScriptColor>23396</ScriptColor>
            <ScriptDuration>10</ScriptDuration>
        </ScriptData>
        <ScriptData>
            <ScriptBright>0</ScriptBright>
            <ScriptColor>20846</ScriptColor>
            <ScriptDuration>10</ScriptDuration>
        </ScriptData>
        <ScriptData>
            <ScriptBright>0</ScriptBright>
            <ScriptColor>18296</ScriptColor>
            <ScriptDuration>10</ScriptDuration>
        </ScriptData>
        <ScriptData>
            <ScriptBright>0</ScriptBright>
            <ScriptColor>15746</ScriptColor>
            <ScriptDuration>10</ScriptDuration>
        </ScriptData>
        <ScriptData>
            <ScriptBright>0</ScriptBright>
            <ScriptColor>13196</ScriptColor>
            <ScriptDuration>10</ScriptDuration>
        </ScriptData>
        <ScriptData>
            <ScriptBright>0</ScriptBright>
            <ScriptColor>10646</ScriptColor>
            <ScriptDuration>10</ScriptDuration>
        </ScriptData>
        <ScriptData>
            <ScriptBright>0</ScriptBright>
            <ScriptColor>8096</ScriptColor>
            <ScriptDuration>10</ScriptDuration>
        </ScriptData>
        <ScriptData>
            <ScriptBright>0</ScriptBright>
            <ScriptColor>5546</ScriptColor>
            <ScriptDuration>10</ScriptDuration>
        </ScriptData>
        <ScriptData>
            <ScriptBright>0</ScriptBright>
            <ScriptColor>2996</ScriptColor>
            <ScriptDuration>10</ScriptDuration>
        </ScriptData>
        <ScriptData>
            <ScriptBright>0</ScriptBright>
            <ScriptColor>191</ScriptColor>
            <ScriptDuration>200</ScriptDuration>
        </ScriptData>
        <ScriptData>
            <ScriptBright>0</ScriptBright>
            <ScriptColor>655541</ScriptColor>
            <ScriptDuration>10</ScriptDuration>
        </ScriptData>
        <ScriptData>
            <ScriptBright>0</ScriptBright>
            <ScriptColor>1310891</ScriptColor>
            <ScriptDuration>10</ScriptDuration>
        </ScriptData>
        <ScriptData>
            <ScriptBright>0</ScriptBright>
            <ScriptColor>1966241</ScriptColor>
            <ScriptDuration>10</ScriptDuration>
        </ScriptData>
        <ScriptData>
            <ScriptBright>0</ScriptBright>
            <ScriptColor>2621591</ScriptColor>
            <ScriptDuration>10</ScriptDuration>
        </ScriptData>
        <ScriptData>
            <ScriptBright>0</ScriptBright>
            <ScriptColor>3276941</ScriptColor>
            <ScriptDuration>10</ScriptDuration>
        </ScriptData>
        <ScriptData>
            <ScriptBright>0</ScriptBright>
            <ScriptColor>3932291</ScriptColor>
            <ScriptDuration>10</ScriptDuration>
        </ScriptData>
        <ScriptData>
            <ScriptBright>0</ScriptBright>
            <ScriptColor>4587641</ScriptColor>
            <ScriptDuration>10</ScriptDuration>
        </ScriptData>
        <ScriptData>
            <ScriptBright>0</ScriptBright>
            <ScriptColor>5242991</ScriptColor>
            <ScriptDuration>10</ScriptDuration>
        </ScriptData>
        <ScriptData>
            <ScriptBright>0</ScriptBright>
            <ScriptColor>5898341</ScriptColor>
            <ScriptDuration>10</ScriptDuration>
        </ScriptData>
        <ScriptData>
            <ScriptBright>0</ScriptBright>
            <ScriptColor>6553691</ScriptColor>
            <ScriptDuration>10</ScriptDuration>
        </ScriptData>
        <ScriptData>
            <ScriptBright>0</ScriptBright>
            <ScriptColor>7209041</ScriptColor>
            <ScriptDuration>10</ScriptDuration>
        </ScriptData>
        <ScriptData>
            <ScriptBright>0</ScriptBright>
            <ScriptColor>7864391</ScriptColor>
            <ScriptDuration>10</ScriptDuration>
        </ScriptData>
        <ScriptData>
            <ScriptBright>0</ScriptBright>
            <ScriptColor>8519741</ScriptColor>
            <ScriptDuration>10</ScriptDuration>
        </ScriptData>
        <ScriptData>
            <ScriptBright>0</ScriptBright>
            <ScriptColor>9175091</ScriptColor>
            <ScriptDuration>10</ScriptDuration>
        </ScriptData>
        <ScriptData>
            <ScriptBright>0</ScriptBright>
            <ScriptColor>9830441</ScriptColor>
            <ScriptDuration>10</ScriptDuration>
        </ScriptData>
        <ScriptData>
            <ScriptBright>0</ScriptBright>
            <ScriptColor>10485791</ScriptColor>
            <ScriptDuration>10</ScriptDuration>
        </ScriptData>
        <ScriptData>
            <ScriptBright>0</ScriptBright>
            <ScriptColor>11141141</ScriptColor>
            <ScriptDuration>10</ScriptDuration>
        </ScriptData>
        <ScriptData>
            <ScriptBright>0</ScriptBright>
            <ScriptColor>11796491</ScriptColor>
            <ScriptDuration>10</ScriptDuration>
        </ScriptData>
        <ScriptData>
            <ScriptBright>OP_END</ScriptBright>
            <ScriptDuration>0</ScriptDuration>
        </ScriptData>
    </ScriptDataList>
</Script>